data_cook/__init__.py
data_cook/csv/__init__.py
data_cook/csv/group/__init__.py
data_cook/csv/group/data_group.py
data_cook/csv/group/group_and_aggregate.py
data_cook/csv/group/group_and_filter.py
data_cook/csv/group/group_and_merge.py
data_cook/csv/group/group_and_rank.py
data_cook/csv/group/group_and_split.py
data_cook/csv/group/group_and_transform.py
data_cook/csv/join/__init__.py
data_cook/csv/join/async_join.py
data_cook/csv/join/basic_join.py
data_cook/csv/join/conditional_join.py
data_cook/csv/join/index_join.py
data_cook/csv/join/join_with_suffix.py
data_cook/csv/join/multi_column_join.py
data_cook/csv/merge/__init__.py
data_cook/csv/merge/async_merge.py
data_cook/csv/merge/basic_merge.py
data_cook/csv/merge/conditional_merge.py
data_cook/csv/merge/merge_by_condition_and_group.py
data_cook/csv/merge/merge_by_group.py
data_cook/csv/merge/merge_by_group_and_condition.py
data_cook/csv/merge/merge_with_operation.py
data_cook/csv/merge/merge_with_suffix.py
data_cook/csv/merge/multi_column_merge.py
data_cook/csv/preprocessing/__init__.py
data_cook/csv/split/__init__.py
data_cook/csv/split/data_split.py
data_cook/csv/split/data_split_by_condition.py
data_cook/csv/split/data_split_by_distribution.py
data_cook/csv/split/data_split_by_group.py
data_cook/csv/split/data_split_cross_validation.py
data_cook/csv/split/data_split_custom_ratio.py
data_cook/csv/split/data_split_stratified.py
data_cook/csv/split/data_split_time_series.py
data_cook/csv_cook/__init__.py
data_cook/csv_cook/group/__init__.py
data_cook/csv_cook/group/data_group.py
data_cook/csv_cook/group/group_and_aggregate.py
data_cook/csv_cook/group/group_and_filter.py
data_cook/csv_cook/group/group_and_merge.py
data_cook/csv_cook/group/group_and_rank.py
data_cook/csv_cook/group/group_and_split.py
data_cook/csv_cook/group/group_and_transform.py
data_cook/csv_cook/join/__init__.py
data_cook/csv_cook/join/async_join.py
data_cook/csv_cook/join/basic_join.py
data_cook/csv_cook/join/conditional_join.py
data_cook-0.2.0.dist-info/licenses/LICENSE
data_cook-0.2.0.dist-info/METADATA
data_cook-0.2.0.dist-info/WHEEL
data_cook-0.2.0.dist-info/top_level.txt
data_cook-0.2.0.dist-info/RECORD
